inputlib/__init__.py
inputlib-0.0.1.dist-info/DESCRIPTION.rst
inputlib-0.0.1.dist-info/METADATA
inputlib-0.0.1.dist-info/RECORD
inputlib-0.0.1.dist-info/WHEEL
inputlib-0.0.1.dist-info/metadata.json
inputlib-0.0.1.dist-info/top_level.txt
