Metadata-Version: 2.0
Name: inputlib
Version: 0.0.1
Summary: make inputting python urls easy!
Home-page: https://github.com/therealadityashankar/inputlib
Author: Aditya Shankar
Author-email: aditniru@gmail.com
License: Unlicence
Platform: UNKNOWN
